[
    {
        "id": "1",
        "name": "The Fool",
        "image_url": "/forward/m00.jpg"
    },
    {
        "id": "2",
        "name": "The Magician",
        "image_url": "/forward/m01.jpg"
    },
    {
        "id": "3",
        "name": "The High Priestess",
        "image_url": "/forward/m02.jpg"
    },
    {
        "id": "4",
        "name": "The Empress",
        "image_url": "/forward/m03.jpg"
    },
    {
        "id": "5",
        "name": "The Emperor",
        "image_url": "/forward/m04.jpg"
    },
    {
        "id": "6",
        "name": "The Hierophant",
        "image_url": "/forward/m05.jpg"
    },
    {
        "id": "7",
        "name": "The Lovers",
        "image_url": "/forward/m06.jpg"
    },
    {
        "id": "8",
        "name": "The Chariot",
        "image_url": "/forward/m07.jpg"
    },
    {
        "id": "9",
        "name": "Strength",
        "image_url": "/forward/m08.jpg"
    },
    {
        "id": "10",
        "name": "The Hermit",
        "image_url": "/forward/m09.jpg"
    },
    {
        "id": "11",
        "name": "Wheel of Fortune",
        "image_url": "/forward/m10.jpg"
    },
    {
        "id": "12",
        "name": "Justice",
        "image_url": "/forward/m11.jpg"
    },
    {
        "id": "13",
        "name": "The Hanged Man",
        "image_url": "/forward/m12.jpg"
    },
    {
        "id": "14",
        "name": "Death",
        "image_url": "/forward/m13.jpg"
    },
    {
        "id": "15",
        "name": "Temperance",
        "image_url": "/forward/m14.jpg"
    },
    {
        "id": "16",
        "name": "The Devil",
        "image_url": "/forward/m15.jpg"
    },
    {
        "id": "17",
        "name": "The Tower",
        "image_url": "/forward/m16.jpg"
    },
    {
        "id": "18",
        "name": "The Star",
        "image_url": "/forward/m17.jpg"
    },
    {
        "id": "19",
        "name": "The Moon",
        "image_url": "/forward/m18.jpg"
    },
    {
        "id": "20",
        "name": "The Sun",
        "image_url": "/forward/m19.jpg"
    },
    {
        "id": "21",
        "name": "Judgement",
        "image_url": "/forward/m20.jpg"
    },
    {
        "id": "22",
        "name": "The World",
        "image_url": "/forward/m21.jpg"
    },
    {
        "id": "23",
        "name": "Ace of Cups",
        "image_url": "/forward/c01.jpg"
    },
    {
        "id": "24",
        "name": "Two of Cups",
        "image_url": "/forward/c02.jpg"
    },
    {
        "id": "25",
        "name": "Three of Cups",
        "image_url": "/forward/c03.jpg"
    },
    {
        "id": "26",
        "name": "Four of Cups",
        "image_url": "/forward/c04.jpg"
    },
    {
        "id": "27",
        "name": "Five of Cups",
        "image_url": "/forward/c05.jpg"
    },
    {
        "id": "28",
        "name": "Six of Cups",
        "image_url": "/forward/c06.jpg"
    },
    {
        "id": "29",
        "name": "Seven of Cups",
        "image_url": "/forward/c07.jpg"
    },
    {
        "id": "30",
        "name": "Eight of Cups",
        "image_url": "/forward/c08.jpg"
    },
    {
        "id": "31",
        "name": "Nine of Cups",
        "image_url": "/forward/c09.jpg"
    },
    {
        "id": "32",
        "name": "Ten of Cups",
        "image_url": "/forward/c10.jpg"
    },
    {
        "id": "33",
        "name": "Page of Cups",
        "image_url": "/forward/c11.jpg"
    },
    {
        "id": "34",
        "name": "Knight of Cups",
        "image_url": "/forward/c12.jpg"
    },
    {
        "id": "35",
        "name": "Queen of Cups",
        "image_url": "/forward/c13.jpg"
    },
    {
        "id": "36",
        "name": "King of Cups",
        "image_url": "/forward/c14.jpg"
    },
    {
        "id": "37",
        "name": "Ace of Swords",
        "image_url": "/forward/s01.jpg"
    },
    {
        "id": "38",
        "name": "Two of Swords",
        "image_url": "/forward/s02.jpg"
    },
    {
        "id": "39",
        "name": "Three of Swords",
        "image_url": "/forward/s03.jpg"
    },
    {
        "id": "40",
        "name": "Four of Swords",
        "image_url": "/forward/s04.jpg"
    },
    {
        "id": "41",
        "name": "Five of Swords",
        "image_url": "/forward/s05.jpg"
    },
    {
        "id": "42",
        "name": "Six of Swords",
        "image_url": "/forward/s06.jpg"
    },
    {
        "id": "43",
        "name": "Seven of Swords",
        "image_url": "/forward/s07.jpg"
    },
    {
        "id": "44",
        "name": "Eight of Swords",
        "image_url": "/forward/s08.jpg"
    },
    {
        "id": "45",
        "name": "Nine of Swords",
        "image_url": "/forward/s09.jpg"
    },
    {
        "id": "46",
        "name": "Ten of Swords",
        "image_url": "/forward/s10.jpg"
    },
    {
        "id": "47",
        "name": "Page of Swords",
        "image_url": "/forward/s11.jpg"
    },
    {
        "id": "48",
        "name": "Knight of Swords",
        "image_url": "/forward/s12.jpg"
    },
    {
        "id": "49",
        "name": "Queen of Swords",
        "image_url": "/forward/s13.jpg"
    },
    {
        "id": "50",
        "name": "King of Swords",
        "image_url": "/forward/s14.jpg"
    },
    {
        "id": "51",
        "name": "Ace of Wands",
        "image_url": "/forward/w01.jpg"
    },
    {
        "id": "52",
        "name": "Two of Wands",
        "image_url": "/forward/w02.jpg"
    },
    {
        "id": "53",
        "name": "Three of Wands",
        "image_url": "/forward/w03.jpg"
    },
    {
        "id": "54",
        "name": "Four of Wands",
        "image_url": "/forward/w04.jpg"
    },
    {
        "id": "55",
        "name": "Five of Wands",
        "image_url": "/forward/w05.jpg"
    },
    {
        "id": "56",
        "name": "Six of Wands",
        "image_url": "/forward/w06.jpg"
    },
    {
        "id": "57",
        "name": "Seven of Wands",
        "image_url": "/forward/w07.jpg"
    },
    {
        "id": "58",
        "name": "Eight of Wands",
        "image_url": "/forward/w08.jpg"
    },
    {
        "id": "59",
        "name": "Nine of Wands",
        "image_url": "/forward/w09.jpg"
    },
    {
        "id": "60",
        "name": "Ten of Wands",
        "image_url": "/forward/w10.jpg"
    },
    {
        "id": "61",
        "name": "Page of Wands",
        "image_url": "/forward/w11.jpg"
    },
    {
        "id": "62",
        "name": "Knight of Wands",
        "image_url": "/forward/w12.jpg"
    },
    {
        "id": "63",
        "name": "Queen of Wands",
        "image_url": "/forward/w13.jpg"
    },
    {
        "id": "64",
        "name": "King of Wands",
        "image_url": "/forward/w14.jpg"
    },
    {
        "id": "65",
        "name": "Ace of Pentacles",
        "image_url": "/forward/p01.jpg"
    },
    {
        "id": "66",
        "name": "Two of Pentacles",
        "image_url": "/forward/p02.jpg"
    },
    {
        "id": "67",
        "name": "Three of Pentacles",
        "image_url": "/forward/p03.jpg"
    },
    {
        "id": "68",
        "name": "Four of Pentacles",
        "image_url": "/forward/p04.jpg"
    },
    {
        "id": "69",
        "name": "Five of Pentacles",
        "image_url": "/forward/p05.jpg"
    },
    {
        "id": "70",
        "name": "Six of Pentacles",
        "image_url": "/forward/p06.jpg"
    },
    {
        "id": "71",
        "name": "Seven of Pentacles",
        "image_url": "/forward/p07.jpg"
    },
    {
        "id": "72",
        "name": "Eight of Pentacles",
        "image_url": "/forward/p08.jpg"
    },
    {
        "id": "73",
        "name": "Nine of Pentacles",
        "image_url": "/forward/p09.jpg"
    },
    {
        "id": "74",
        "name": "Ten of Pentacles",
        "image_url": "/forward/p10.jpg"
    },
    {
        "id": "75",
        "name": "Page of Pentacles",
        "image_url": "/forward/p11.jpg"
    },
    {
        "id": "76",
        "name": "Knight of Pentacles",
        "image_url": "/forward/p12.jpg"
    },
    {
        "id": "77",
        "name": "Queen of Pentacles",
        "image_url": "/forward/p13.jpg"
    },
    {
        "id": "78",
        "name": "King of Pentacles",
        "image_url": "/forward/p14.jpg"
    },
    {
        "id": "79",
        "name": "The Fool ngược",
        "image_url": "/reverse/m00_r.jpg"
    },
    {
        "id": "80",
        "name": "The Magician ngược",
        "image_url": "/reverse/m01_r.jpg"
    },
    {
        "id": "81",
        "name": "The High Priestess ngược",
        "image_url": "/reverse/m02_r.jpg"
    },
    {
        "id": "82",
        "name": "The Empress ngược",
        "image_url": "/reverse/m03_r.jpg"
    },
    {
        "id": "83",
        "name": "The Emperor ngược",
        "image_url": "/reverse/m04_r.jpg"
    },
    {
        "id": "84",
        "name": "The Hierophant ngược",
        "image_url": "/reverse/m05_r.jpg"
    },
    {
        "id": "85",
        "name": "The Lovers ngược",
        "image_url": "/reverse/m06_r.jpg"
    },
    {
        "id": "86",
        "name": "The Chariot ngược",
        "image_url": "/reverse/m07_r.jpg"
    },
    {
        "id": "87",
        "name": "Strength ngược",
        "image_url": "/reverse/m08_r.jpg"
    },
    {
        "id": "88",
        "name": "The Hermit ngược",
        "image_url": "/reverse/m09_r.jpg"
    },
    {
        "id": "89",
        "name": "Wheel of Fortune ngược",
        "image_url": "/reverse/m10_r.jpg"
    },
    {
        "id": "90",
        "name": "Justice ngược",
        "image_url": "/reverse/m11_r.jpg"
    },
    {
        "id": "91",
        "name": "The Hanged Man ngược",
        "image_url": "/reverse/m12_r.jpg"
    },
    {
        "id": "92",
        "name": "Death ngược",
        "image_url": "/reverse/m13_r.jpg"
    },
    {
        "id": "93",
        "name": "Temperance ngược",
        "image_url": "/reverse/m14_r.jpg"
    },
    {
        "id": "94",
        "name": "The Devil ngược",
        "image_url": "/reverse/m15_r.jpg"
    },
    {
        "id": "95",
        "name": "The Tower ngược",
        "image_url": "/reverse/m16_r.jpg"
    },
    {
        "id": "96",
        "name": "The Star ngược",
        "image_url": "/reverse/m17_r.jpg"
    },
    {
        "id": "97",
        "name": "The Moon ngược",
        "image_url": "/reverse/m18_r.jpg"
    },
    {
        "id": "98",
        "name": "The Sun ngược",
        "image_url": "/reverse/m19_r.jpg"
    },
    {
        "id": "99",
        "name": "Judgement ngược",
        "image_url": "/reverse/m20_r.jpg"
    },
    {
        "id": "100",
        "name": "The World ngược",
        "image_url": "/reverse/m21_r.jpg"
    },
    {
        "id": "101",
        "name": "Ace of Cups ngược",
        "image_url": "/reverse/c01_r.jpg"
    },
    {
        "id": "102",
        "name": "Two of Cups ngược",
        "image_url": "/reverse/c02_r.jpg"
    },
    {
        "id": "103",
        "name": "Three of Cups ngược",
        "image_url": "/reverse/c03_r.jpg"
    },
    {
        "id": "104",
        "name": "Four of Cups ngược",
        "image_url": "/reverse/c04_r.jpg"
    },
    {
        "id": "105",
        "name": "Five of Cups ngược",
        "image_url": "/reverse/c05_r.jpg"
    },
    {
        "id": "106",
        "name": "Six of Cups ngược",
        "image_url": "/reverse/c06_r.jpg"
    },
    {
        "id": "107",
        "name": "Seven of Cups ngược",
        "image_url": "/reverse/c07_r.jpg"
    },
    {
        "id": "108",
        "name": "Eight of Cups ngược",
        "image_url": "/reverse/c08_r.jpg"
    },
    {
        "id": "109",
        "name": "Nine of Cups ngược",
        "image_url": "/reverse/c09_r.jpg"
    },
    {
        "id": "110",
        "name": "Ten of Cups ngược",
        "image_url": "/reverse/c10_r.jpg"
    },
    {
        "id": "111",
        "name": "Page of Cups ngược",
        "image_url": "/reverse/c11_r.jpg"
    },
    {
        "id": "112",
        "name": "Knight of Cups ngược",
        "image_url": "/reverse/c12_r.jpg"
    },
    {
        "id": "113",
        "name": "Queen of Cups ngược",
        "image_url": "/reverse/c13_r.jpg"
    },
    {
        "id": "114",
        "name": "King of Cups ngược",
        "image_url": "/reverse/c14_r.jpg"
    },
    {
        "id": "115",
        "name": "Ace of Swords ngược",
        "image_url": "/reverse/s01_r.jpg"
    },
    {
        "id": "116",
        "name": "Two of Swords ngược",
        "image_url": "/reverse/s02_r.jpg"
    },
    {
        "id": "117",
        "name": "Three of Swords ngược",
        "image_url": "/reverse/s03_r.jpg"
    },
    {
        "id": "118",
        "name": "Four of Swords ngược",
        "image_url": "/reverse/s04_r.jpg"
    },
    {
        "id": "119",
        "name": "Five of Swords ngược",
        "image_url": "/reverse/s05_r.jpg"
    },
    {
        "id": "120",
        "name": "Six of Swords ngược",
        "image_url": "/reverse/s06_r.jpg"
    },
    {
        "id": "121",
        "name": "Seven of Swords ngược",
        "image_url": "/reverse/s07_r.jpg"
    },
    {
        "id": "122",
        "name": "Eight of Swords ngược",
        "image_url": "/reverse/s08_r.jpg"
    },
    {
        "id": "123",
        "name": "Nine of Swords ngược",
        "image_url": "/reverse/s09_r.jpg"
    },
    {
        "id": "124",
        "name": "Ten of Swords ngược",
        "image_url": "/reverse/s10_r.jpg"
    },
    {
        "id": "125",
        "name": "Page of Swords ngược",
        "image_url": "/reverse/s11_r.jpg"
    },
    {
        "id": "126",
        "name": "Knight of Swords ngược",
        "image_url": "/reverse/s12_r.jpg"
    },
    {
        "id": "127",
        "name": "Queen of Swords ngược",
        "image_url": "/reverse/s13_r.jpg"
    },
    {
        "id": "128",
        "name": "King of Swords ngược",
        "image_url": "/reverse/s14_r.jpg"
    },
    {
        "id": "129",
        "name": "Ace of Wands ngược",
        "image_url": "/reverse/w01_r.jpg"
    },
    {
        "id": "130",
        "name": "Two of Wands ngược",
        "image_url": "/reverse/w02_r.jpg"
    },
    {
        "id": "131",
        "name": "Three of Wands ngược",
        "image_url": "/reverse/w03_r.jpg"
    },
    {
        "id": "132",
        "name": "Four of Wands ngược",
        "image_url": "/reverse/w04_r.jpg"
    },
    {
        "id": "133",
        "name": "Five of Wands ngược",
        "image_url": "/reverse/w05_r.jpg"
    },
    {
        "id": "134",
        "name": "Six of Wands ngược",
        "image_url": "/reverse/w06_r.jpg"
    },
    {
        "id": "135",
        "name": "Seven of Wands ngược",
        "image_url": "/reverse/w07_r.jpg"
    },
    {
        "id": "136",
        "name": "Eight of Wands ngược",
        "image_url": "/reverse/w08_r.jpg"
    },
    {
        "id": "137",
        "name": "Nine of Wands ngược",
        "image_url": "/reverse/w09_r.jpg"
    },
    {
        "id": "138",
        "name": "Ten of Wands ngược",
        "image_url": "/reverse/w10_r.jpg"
    },
    {
        "id": "139",
        "name": "Page of Wands ngược",
        "image_url": "/reverse/w11_r.jpg"
    },
    {
        "id": "140",
        "name": "Knight of Wands ngược",
        "image_url": "/reverse/w12_r.jpg"
    },
    {
        "id": "141",
        "name": "Queen of Wands ngược",
        "image_url": "/reverse/w13_r.jpg"
    },
    {
        "id": "142",
        "name": "King of Wands ngược",
        "image_url": "/reverse/w14_r.jpg"
    },
    {
        "id": "143",
        "name": "Ace of Pentacles ngược",
        "image_url": "/reverse/p01_r.jpg"
    },
    {
        "id": "144",
        "name": "Two of Pentacles ngược",
        "image_url": "/reverse/p02_r.jpg"
    },
    {
        "id": "145",
        "name": "Three of Pentacles ngược",
        "image_url": "/reverse/p03_r.jpg"
    },
    {
        "id": "146",
        "name": "Four of Pentacles ngược",
        "image_url": "/reverse/p04_r.jpg"
    },
    {
        "id": "147",
        "name": "Five of Pentacles ngược",
        "image_url": "/reverse/p05_r.jpg"
    },
    {
        "id": "148",
        "name": "Six of Pentacles ngược",
        "image_url": "/reverse/p06_r.jpg"
    },
    {
        "id": "149",
        "name": "Seven of Pentacles ngược",
        "image_url": "/reverse/p07_r.jpg"
    },
    {
        "id": "150",
        "name": "Eight of Pentacles ngược",
        "image_url": "/reverse/p08_r.jpg"
    },
    {
        "id": "151",
        "name": "Nine of Pentacles ngược",
        "image_url": "/reverse/p09_r.jpg"
    },
    {
        "id": "152",
        "name": "Ten of Pentacles ngược",
        "image_url": "/reverse/p10_r.jpg"
    },
    {
        "id": "153",
        "name": "Page of Pentacles ngược",
        "image_url": "/reverse/p11_r.jpg"
    },
    {
        "id": "154",
        "name": "Knight of Pentacles ngược",
        "image_url": "/reverse/p12_r.jpg"
    },
    {
        "id": "155",
        "name": "Queen of Pentacles ngược",
        "image_url": "/reverse/p13_r.jpg"
    },
    {
        "id": "156",
        "name": "King of Pentacles ngược",
        "image_url": "/reverse/p14_r.jpg"
    }
]